{
  "niche": "best index funds for beginners",
  "clusters": [
    {
      "cluster": "for beginners",
      "keyword_count": 41,
      "total_volume_estimate": 39778,
      "avg_competition": 63.0,
      "avg_rpm": 20.71,
      "avg_feasibility": 77.9,
      "commercial_ratio": 1.0,
      "cluster_score": 0.01,
      "top_keywords": [
        "best best index funds for beginners reddit",
        "best best index funds for beginners for beginners",
        "best index funds for beginners amazon",
        "top best index funds for beginners reddit",
        "top best index funds for beginners youtube"
      ],
      "content_strategy": "Product-focused content with affiliate integrations. Comparison articles, best-of lists, buying guides."
    }
  ]
}